mcpi/__init__.py
mcpi/block.py
mcpi/connection.py
mcpi/entity.py
mcpi/event.py
mcpi/minecraft.py
mcpi/util.py
mcpi/vec3.py
mcpi-1.2.1.dist-info/LICENSE
mcpi-1.2.1.dist-info/METADATA
mcpi-1.2.1.dist-info/WHEEL
mcpi-1.2.1.dist-info/top_level.txt
mcpi-1.2.1.dist-info/RECORD
